enovates_modbus/__init__.py
enovates_modbus/__main__.py
enovates_modbus/base.py
enovates_modbus/eno_one.py
enovates_modbus-0.1.4.dist-info/licenses/LICENSE.md
enovates_modbus-0.1.4.dist-info/WHEEL
enovates_modbus-0.1.4.dist-info/entry_points.txt
enovates_modbus-0.1.4.dist-info/METADATA
enovates_modbus-0.1.4.dist-info/RECORD
