Metadata-Version: 2.4
Name: enovates-modbus
Version: 0.1.4
Summary: Library for Modbus TCP communication with Enovates EVSE
Keywords: home,automation,enovates,evse
Author: Enovates NV, Dries Kennes
Author-email: Dries Kennes <dries.kennes@gmail.com>
License-Expression: Apache-2.0
License-File: LICENSE.md
Classifier: Intended Audience :: Developers
Classifier: Operating System :: OS Independent
Classifier: Programming Language :: Python :: 3.13
Classifier: Programming Language :: Python :: 3.14
Classifier: Topic :: Home Automation
Requires-Dist: pymodbus>=3.11.2
Requires-Python: >=3.13.2
Project-URL: Homepage, https://www.enovates.com/
Project-URL: Repository, https://github.com/enovates/enovates-modbus
Project-URL: Issues, https://github.com/enovates/enovates-modbus/issues
